parchords_jupyter/__init__.py
parchords_jupyter/_frontend.py
parchords_jupyter/_version.py
parchords_jupyter/parchords_widget.py
parchords_jupyter/labextension/build_log.json
parchords_jupyter/labextension/package.json
parchords_jupyter/labextension/static/lib_index_js.6b63e0a21bab8f71744e.js
parchords_jupyter/labextension/static/lib_index_js.6b63e0a21bab8f71744e.js.map
parchords_jupyter/labextension/static/lib_plugin_js.16d31576d48c01a0c9dc.js
parchords_jupyter/labextension/static/lib_plugin_js.16d31576d48c01a0c9dc.js.map
parchords_jupyter/labextension/static/lib_widget_js.362669f3acdf93a28526.js
parchords_jupyter/labextension/static/lib_widget_js.362669f3acdf93a28526.js.map
parchords_jupyter/labextension/static/lib_widget_js.a6ee9e2b56911aff85f2.js
parchords_jupyter/labextension/static/lib_widget_js.a6ee9e2b56911aff85f2.js.map
parchords_jupyter/labextension/static/lib_widget_js.c131cd7dc4cc7a8e0998.js
parchords_jupyter/labextension/static/lib_widget_js.c131cd7dc4cc7a8e0998.js.map
parchords_jupyter/labextension/static/lib_widget_js.c2deab586074f64bbc2e.js
parchords_jupyter/labextension/static/lib_widget_js.c2deab586074f64bbc2e.js.map
parchords_jupyter/labextension/static/lib_widget_js.c882da089dde56bbe886.js
parchords_jupyter/labextension/static/lib_widget_js.c882da089dde56bbe886.js.map
parchords_jupyter/labextension/static/lib_widget_js.ceb5059ee144027b909e.js
parchords_jupyter/labextension/static/lib_widget_js.ceb5059ee144027b909e.js.map
parchords_jupyter/labextension/static/lib_widget_js.d7c9e61f3004885e1300.js
parchords_jupyter/labextension/static/lib_widget_js.d7c9e61f3004885e1300.js.map
parchords_jupyter/labextension/static/lib_widget_js.ed001eaacec4a84b029a.js
parchords_jupyter/labextension/static/lib_widget_js.ed001eaacec4a84b029a.js.map
parchords_jupyter/labextension/static/lib_widget_js.fe55b52cf22634a93814.js
parchords_jupyter/labextension/static/lib_widget_js.fe55b52cf22634a93814.js.map
parchords_jupyter-0.1.1.dist-info/METADATA
parchords_jupyter-0.1.1.dist-info/WHEEL
parchords_jupyter-0.1.1.dist-info/licenses/LICENSE
parchords_jupyter-0.1.1.dist-info/RECORD
